medvision/__init__.py
medvision/cli/__init__.py
medvision/cli/main.py
medvision/datasets/__init__.py
medvision/datasets/color_dataset.py
medvision/datasets/medical_dataset.py
medvision/losses/__init__.py
medvision/losses/combined.py
medvision/losses/crossentropy.py
medvision/losses/dice.py
medvision/losses/factory.py
medvision/losses/focal.py
medvision/metrics/__init__.py
medvision/metrics/accuracy.py
medvision/metrics/dice.py
medvision/metrics/factory.py
medvision/metrics/hausdorff.py
medvision/metrics/iou.py
medvision/models/ FCN32s.py
medvision/models/ResNetUnetPlus.py
medvision/models/UNet_2Plus.py
medvision/models/UNet_3Plus.py
medvision/models/Unet3d.py
medvision/models/__init__.py
medvision/models/cenet.py
medvision/models/denseUnet.py
medvision/models/model_factory.py
medvision/models/u2net.py
medvision/models/unet.py
medvision/transforms/__init__.py
medvision/transforms/color_transforms.py
medvision/transforms/monai_transforms.py
medvision/utils/__init__.py
medvision/utils/common.py
medvision/utils/config.py
medvision/utils/evaluator.py
medvision/utils/inference.py
medvision/utils/io.py
medvision/utils/onnx_utils.py
medvision/utils/trainer.py
medvision_segmentation-0.3.8.dist-info/licenses/LICENSE
medvision_segmentation-0.3.8.dist-info/METADATA
medvision_segmentation-0.3.8.dist-info/WHEEL
medvision_segmentation-0.3.8.dist-info/entry_points.txt
medvision_segmentation-0.3.8.dist-info/top_level.txt
medvision_segmentation-0.3.8.dist-info/RECORD
