Metadata-Version: 2.4
Name: medvision-segmentation
Version: 0.3.8
Summary: A medical image segmentation framework based on PyTorch Lightning
Home-page: https://github.com/Hi-Zhipeng/MedVision
Author: weizhipeng
Author-email: weizhipeng <weizhipeng@shu.edu.cn>
Maintainer-email: weizhipeng <weizhipeng@shu.edu.cn>
License: MIT License
Project-URL: Homepage, https://github.com/Hi-Zhipeng
Project-URL: Repository, https://github.com/Hi-Zhipeng/MedVision
Project-URL: Documentation, https://github.com/Hi-Zhipeng/MedVision/wiki
Project-URL: Bug Tracker, https://github.com/Hi-Zhipeng/MedVision/issues
Keywords: medical imaging,segmentation,pytorch,deep learning,MONAI
Classifier: Development Status :: 3 - Alpha
Classifier: Intended Audience :: Science/Research
Classifier: Intended Audience :: Healthcare Industry
Classifier: License :: OSI Approved :: MIT License
Classifier: Operating System :: OS Independent
Classifier: Programming Language :: Python :: 3
Classifier: Programming Language :: Python :: 3.8
Classifier: Programming Language :: Python :: 3.9
Classifier: Programming Language :: Python :: 3.10
Classifier: Programming Language :: Python :: 3.11
Classifier: Topic :: Scientific/Engineering :: Medical Science Apps.
Classifier: Topic :: Scientific/Engineering :: Artificial Intelligence
Classifier: Topic :: Scientific/Engineering :: Image Processing
Requires-Python: >=3.10
License-File: LICENSE
Requires-Dist: torch>=2.0.0
Requires-Dist: torchvision>=0.15.0
Requires-Dist: pytorch-lightning>=2.0.0
Requires-Dist: lightning>=2.0.0
Requires-Dist: numpy>=1.21.0
Requires-Dist: pyyaml>=6.0
Requires-Dist: tqdm>=4.64.0
Requires-Dist: click>=8.0.0
Requires-Dist: pillow>=9.0.0
Requires-Dist: scikit-image>=0.19.0
Requires-Dist: pandas>=1.4.0
Requires-Dist: onnxscript
Provides-Extra: medical
Requires-Dist: nibabel>=3.2.0; extra == "medical"
Requires-Dist: SimpleITK>=2.2.0; extra == "medical"
Requires-Dist: pydicom>=2.3.0; extra == "medical"
Requires-Dist: vtk>=9.2.0; extra == "medical"
Provides-Extra: transforms
Requires-Dist: monai>=1.3.0; extra == "transforms"
Requires-Dist: torchio>=0.18.0; extra == "transforms"
Requires-Dist: albumentations>=1.3.0; extra == "transforms"
Requires-Dist: opencv-python>=4.7.0; extra == "transforms"
Provides-Extra: visualization
Requires-Dist: matplotlib>=3.6.0; extra == "visualization"
Requires-Dist: seaborn>=0.12.0; extra == "visualization"
Requires-Dist: plotly>=5.10.0; extra == "visualization"
Requires-Dist: tensorboard>=2.10.0; extra == "visualization"
Requires-Dist: wandb>=0.13.0; extra == "visualization"
Provides-Extra: metrics
Requires-Dist: scikit-learn>=1.1.0; extra == "metrics"
Requires-Dist: scipy>=1.9.0; extra == "metrics"
Requires-Dist: surface-distance>=0.1.0; extra == "metrics"
Requires-Dist: hausdorff>=0.2.6; extra == "metrics"
Provides-Extra: dev
Requires-Dist: pytest>=7.0.0; extra == "dev"
Requires-Dist: pytest-cov>=4.0.0; extra == "dev"
Requires-Dist: black>=22.0.0; extra == "dev"
Requires-Dist: isort>=5.10.0; extra == "dev"
Requires-Dist: flake8>=5.0.0; extra == "dev"
Requires-Dist: mypy>=0.991; extra == "dev"
Requires-Dist: pre-commit>=2.20.0; extra == "dev"
Provides-Extra: docs
Requires-Dist: sphinx>=5.0.0; extra == "docs"
Requires-Dist: sphinx-rtd-theme>=1.2.0; extra == "docs"
Requires-Dist: myst-parser>=0.18.0; extra == "docs"
Provides-Extra: export
Requires-Dist: onnx>=1.12.0; extra == "export"
Requires-Dist: onnxruntime>=1.12.0; extra == "export"
Provides-Extra: all
Requires-Dist: nibabel>=3.2.0; extra == "all"
Requires-Dist: SimpleITK>=2.2.0; extra == "all"
Requires-Dist: pydicom>=2.3.0; extra == "all"
Requires-Dist: vtk>=9.2.0; extra == "all"
Requires-Dist: monai>=1.3.0; extra == "all"
Requires-Dist: torchio>=0.18.0; extra == "all"
Requires-Dist: albumentations>=1.3.0; extra == "all"
Requires-Dist: opencv-python>=4.7.0; extra == "all"
Requires-Dist: matplotlib>=3.6.0; extra == "all"
Requires-Dist: seaborn>=0.12.0; extra == "all"
Requires-Dist: plotly>=5.10.0; extra == "all"
Requires-Dist: tensorboard>=2.10.0; extra == "all"
Requires-Dist: wandb>=0.13.0; extra == "all"
Requires-Dist: scikit-learn>=1.1.0; extra == "all"
Requires-Dist: scipy>=1.9.0; extra == "all"
Requires-Dist: surface-distance>=0.1.0; extra == "all"
Requires-Dist: hausdorff>=0.2.6; extra == "all"
Requires-Dist: onnx>=1.12.0; extra == "all"
Requires-Dist: onnxruntime>=1.12.0; extra == "all"
Requires-Dist: onnxscript==0.5.4; extra == "all"
Requires-Dist: segmentation_models_pytorch; extra == "all"
Dynamic: author
Dynamic: home-page
Dynamic: license-file
Dynamic: requires-python
